BingImageCreator.py
BingImageCreator-0.5.0.dist-info/LICENSE
BingImageCreator-0.5.0.dist-info/METADATA
BingImageCreator-0.5.0.dist-info/WHEEL
BingImageCreator-0.5.0.dist-info/top_level.txt
BingImageCreator-0.5.0.dist-info/RECORD
