Metadata-Version: 2.1
Name: BingImageCreator
Version: 0.5.0
Summary: High quality image generation by Microsoft. Reverse engineered API.
Home-page: https://github.com/acheong08/BingImageCreator
Author: Antonio Cheong
Author-email: acheong@student.dalat.org
License: GNU General Public License v2.0
Project-URL: Bug Report, https://github.com/acheong08/BingImageCreator/issues/new
Classifier: License :: OSI Approved :: GNU General Public License v2 (GPLv2)
Classifier: Intended Audience :: Developers
Classifier: Topic :: Software Development :: Libraries :: Python Modules
Classifier: Programming Language :: Python :: 3.8
Classifier: Programming Language :: Python :: 3.9
Classifier: Programming Language :: Python :: 3.10
Classifier: Programming Language :: Python :: 3.11
License-File: LICENSE
